cli/__init__.py
cli/sentinel.py
meile/__init__.py
meile/config.ini
meile/logo.uni
meile/meile.py
meile-0.5.1.dist-info/METADATA
meile-0.5.1.dist-info/WHEEL
meile-0.5.1.dist-info/entry_points.txt
meile-0.5.1.dist-info/top_level.txt
meile-0.5.1.dist-info/RECORD
