Metadata-Version: 2.1
Name: meile
Version: 0.5.1
Summary: Meile dVPN powered by the Sentinel Network
Home-page: https://github.com/MathNodes/meile
Author: MathNodes
Author-email: freQniK@mathnodes.com
License: MIT
Keywords: vpn,dvpn,sentinel,crypto,tui,privacy,security
Classifier: Programming Language :: Python
Classifier: Programming Language :: Python :: 3
Requires-Dist: requests
Requires-Dist: npyscreen
Requires-Dist: prettytable
